django_multidatabase_queryset/__about__.py
django_multidatabase_queryset/__init__.py
django_multidatabase_queryset/admin.py
django_multidatabase_queryset/apps.py
django_multidatabase_queryset/models.py
django_multidatabase_queryset/tests.py
django_multidatabase_queryset/views.py
django_multidatabase_queryset/migrations/__init__.py
django_multidatabase_queryset-0.9.0.dist-info/METADATA
django_multidatabase_queryset-0.9.0.dist-info/WHEEL
django_multidatabase_queryset-0.9.0.dist-info/licenses/LICENSE
django_multidatabase_queryset-0.9.0.dist-info/RECORD
