Metadata-Version: 2.1
Name: django-multidatabase-queryset
Version: 0.9.0
Project-URL: Documentation, https://github.com/unknown/django-multidatabase-queryset#readme
Project-URL: Issues, https://github.com/unknown/django-multidatabase-queryset/issues
Project-URL: Source, https://github.com/unknown/django-multidatabase-queryset
Author-email: Xiang Wang <ramwin@qq.com>
License-Expression: MIT
License-File: LICENSE
Classifier: Development Status :: 4 - Beta
Classifier: Programming Language :: Python
Classifier: Programming Language :: Python :: 3.7
Classifier: Programming Language :: Python :: 3.8
Classifier: Programming Language :: Python :: 3.9
Classifier: Programming Language :: Python :: 3.10
Classifier: Programming Language :: Python :: 3.11
Classifier: Programming Language :: Python :: Implementation :: CPython
Classifier: Programming Language :: Python :: Implementation :: PyPy
Requires-Python: >=3.7
